{
	"name": "autumn-season-dark",
	"displayName": "Autumn Season",
	"type": "dark",
	"colors": {
		"editor.background": "#3d2f26",
		"editor.foreground": "#e1c6b0",
		"editor.hoverHighlightBackground": "#00000000",
		"editor.lineHighlightBackground": "#87715870",
		"editor.selectionBackground": "#5c4b3f",
		"editor.selectionHighlightBackground": "#5c4b3f70",
		"editor.wordHighlightBackground": "#ff683550",
		"editor.wordHighlightStrongBackground": "#ff3b3b70",
		"editor.findMatchBackground": "#e09b5c",
		"editor.findMatchHighlightBackground": "#e09b5c70",
		"editor.findRangeHighlightBackground": "#3d2f2670",
		"editor.inactiveSelectionBackground": "#e09b5c70",
		"editor.lineHighlightBorder": "#877158",
		"editor.rangeHighlightBackground": "#3d2f2670",
		"editorInlayHint.typeBackground": "#d25c3a",
		"editorInlayHint.typeForeground": "#e1c6b0",
		"editorIndentGuide.background1": "#d25c3a",
		"editorHoverWidget.background": "#3d2f26",
		"editorGutter.background": "#3d2f26",
		"editorGutter.modifiedBackground": "#d25c3a",
		"editorGutter.addedBackground": "#e09b5c",
		"editorGutter.deletedBackground": "#ff3b3b",
		"editorBracketMatch.background": "#877158",
		"editorBracketMatch.border": "#877158",
		"editorGroupHeader.tabsBackground": "#3d2f26",
		"editorGroup.border": "#877158",
		"tab.activeBackground": "#7a6c58",
		"tab.inactiveBackground": "#3d2f26",
		"tab.inactiveForeground": "#a57c5a",
		"tab.activeForeground": "#e1c6b0",
		"tab.hoverBackground": "#7a6c58",
		"tab.hoverForeground": "#e1c6b0",
		"tab.unfocusedHoverBackground": "#3d2f26",
		"tab.unfocusedHoverForeground": "#e1c6b0",
		"tab.border": "#877158",
		"tab.activeModifiedBorder": "#e09b5c",
		"tab.inactiveModifiedBorder": "#877158",
		"tab.unfocusedActiveModifiedBorder": "#e09b5c",
		"tab.unfocusedInactiveModifiedBorder": "#877158",
		"editorWidget.background": "#3d2f26",
		"editorWidget.border": "#877158",
		"editorSuggestWidget.background": "#3d2f26",
		"editorSuggestWidget.border": "#877158",
		"editorSuggestWidget.foreground": "#e1c6b0",
		"editorSuggestWidget.highlightForeground": "#a57c5a",
		"editorSuggestWidget.selectedBackground": "#d25c3a",
		"peekView.border": "#877158",
		"peekViewEditor.background": "#3d2f26",
		"peekViewEditor.matchHighlightBackground": "#a57c5a",
		"peekViewResult.background": "#877158",
		"peekViewResult.fileForeground": "#e1c6b0",
		"peekViewResult.lineForeground": "#a57c5a",
		"peekViewResult.matchHighlightBackground": "#a57c5a",
		"peekViewResult.selectionBackground": "#8771586b",
		"peekViewResult.selectionForeground": "#e09b5c",
		"peekViewTitle.background": "#d25c3a",
		"peekViewTitleDescription.foreground": "#a57c5a",
		"peekViewTitleLabel.foreground": "#e1c6b0",
		"merge.currentHeaderBackground": "#e09b5c70",
		"merge.currentContentBackground": "#e09b5c70",
		"merge.incomingHeaderBackground": "#e09b5c70",
		"merge.incomingContentBackground": "#e09b5c70",
		"merge.border": "#877158",
		"merge.commonContentBackground": "#d25c3a70",
		"merge.commonHeaderBackground": "#d25c3a70",
		"panel.background": "#3d2f26",
		"panel.border": "#877158",
		"panelTitle.activeBorder": "#a57c5a",
		"panelTitle.activeForeground": "#e1c6b0",
		"panelTitle.inactiveForeground": "#a57c5a",
		"statusBar.background": "#3d2f26",
		"statusBar.foreground": "#e1c6b0",
		"statusBar.border": "#877158",
		"statusBar.debuggingBackground": "#ff3b3b",
		"statusBar.debuggingForeground": "#e1c6b0",
		"statusBar.noFolderBackground": "#a57c5a",
		"statusBar.noFolderForeground": "#e09b5c",
		"titleBar.activeBackground": "#3d2f26",
		"titleBar.activeForeground": "#e1c6b0",
		"titleBar.inactiveBackground": "#2a2120",
		"titleBar.inactiveForeground": "#a57c5a",
		"titleBar.border": "#877158",
		"input.background": "#3d2f26",
		"input.foreground": "#e1c6b0",
		"input.border": "#877158",
		"focusBorder": "#e5c1b0",
		"input.placeholderForeground": "#a57c5a",
		"inputOption.activeBackground": "#7a6c58",
		"inputOption.activeForeground": "#e1c6b0",
		"inputOption.activeBorder": "#bda27c",
		"inputValidation.infoBorder": "#e09b5c",
		"inputValidation.warningBorder": "#ff6735",
		"inputValidation.errorBorder": "#ff3b3b",   
		"debugToolBar.background": "#3d2f26",
		"debugToolBar.border": "#877158",
		"debugConsole.errorForeground": "#ff3b3b",
		"debugConsole.warningForeground": "#ff6735",
		"debugConsole.infoForeground": "#e1c6b0",
		"editorRuler.foreground": "#e09b5c",
		"scrollbar.shadow": "#d25c3a",
		"scrollbarSlider.background": "#877158",
		"scrollbarSlider.hoverBackground": "#d25c3a",
		"scrollbarSlider.activeBackground": "#ff6735",
		"editorCodeLens.foreground": "#e1c6b0",
		"debugExceptionWidget.background": "#3d2f26",
		"debugExceptionWidget.border": "#877158",
		"editorWarning.foreground": "#ff3b3b",
		"editorInfo.foreground": "#ff6735",
		"editorHint.foreground": "#e09b5c",
		"editorLineNumber.activeForeground": "#e1c6b0",
		"editorLineNumber.foreground": "#a57c5a",
		"editorWhitespace.foreground": "#877158",
		"sideBar.background": "#3d2f26",
		"sideBar.foreground": "#F3D699",
		"sideBar.border": "#877158",
		"activityBar.background": "#3d2f26",
		"activityBar.foreground": "#F3D699",
		"activityBar.activeBorder": "#FFB63F",
		"activityBar.inactiveForeground": "#D4B98B",
		"button.background": "#5c4b3f",
		"button.foreground": "#e1c6b0",
		"button.hoverBackground": "#7a6c58",
		"notifications.background": "#5c4b3f",
		"notifications.foreground": "#e1c6b0",
		"notificationCenterHeader.background": "#3d2f26",
		"notificationCenterHeader.foreground": "#e1c6b0",
		"notificationToast.border": "#877158",
		"notificationsErrorIcon.foreground": "#ff3b3b",
		"notificationsWarningIcon.foreground": "#ff6735",
		"notificationsInfoIcon.foreground": "#e09b5c",
		"dropdown.background": "#4b3a31",
		"dropdown.foreground": "#e1c6b0",
		"list.activeSelectionBackground": "#7a6c58",
		"list.activeSelectionForeground": "#e1c6b0",
		"list.inactiveSelectionBackground": "#4b3a31",
		"list.inactiveSelectionForeground": "#e1c6b0",
		"list.hoverBackground": "#5c4b3f",
		"list.hoverForeground": "#e1c6b0",
		"list.focusBackground": "#a57c5a",
		"list.focusForeground": "#e1c6b0",
		"list.focusOutline": "#ff933400",
		"gitDecoration.modifiedResourceForeground": "#e09b5c",
		"activityBarBadge.background": "#d25c3a",
    	"activityBarBadge.foreground": "#e1c6b0",
		"window.activeBorder": "#3d2f26",
		"window.inactiveBorder": "#3d2f26"
	},
	"tokenColors": [
	  {
		"scope": ["comment"],
		"settings": {
		  "foreground": "#a57c5a"
		}
	  },
	  {
		"name": "Markdown link",
		"scope": [
		  "markup.underline.link.markdown",
		  "markup.underline.link"
		],
		"settings": {
		  "foreground": "#d25c3a"
		}
	  },
	  {
		"scope": [
		  "keyword",
		  "variable.language"
		],
		"settings": {
		  "foreground": "#d25c3a"
		}
	  },
	  {
		"scope": ["variable", "variable.other"],
		"settings": {
		  "foreground": "#ff9334"
		}
	  },
	  {
		"scope": ["string"],
		"settings": {
		  "foreground": "#e09b5c"
		}
	  },
	  {
		"scope": ["constant", "constant.numeric"],
		"settings": {
		  "foreground": "#ff6735"
		}
	  },
	  {
		"scope": ["function"],
		"settings": {
		  "foreground": "#e1c6b0"
		}
	  },
	  {
		"scope": ["type"],
		"settings": {
		  "foreground": "#e1c6b0"
		}
	  },
	  {
		"scope": ["support"],
		"settings": {
		  "foreground": "#d25c3a"
		}
	  },
	  {
		"scope": ["entity.name.tag"],
		"settings": {
		  "foreground": "#ff9334"
		}
	  },
	  {
		"scope": ["meta.object.key"],
		"settings": {
		  "foreground": "#e1c6b0"
		}
	  },
	  {
		"scope": ["meta.object.value"],
		"settings": {
		  "foreground": "#3d2f26"
		}
	  },
	  {
		"scope": ["punctuation.section.block.begin", "punctuation.section.block.end"],
		"settings": {
		  "foreground": "#bda27c"
		}
	  }
	  
	]
}
  